Workbook

Sheet page 1
A1: Reference | B1: Qty | C1: codigo | D1: Descripcion Finengas | E1: Value | F1: Footprint
A2: C1,C2,C3,C4 | B2: 4 | C2: 60024300 | D2: =VLOOKUP(C2,codigo!A:B,2,FALSE) -> CAPACITOR ELECTROLITICO 10µF X 25V | E2: 10uF x 16V | F2: Capacitor_THT:CP_Radial_D5.0mm_P2.00mm
A3: C5,C6,C8,C9,C10,C11 | B3: 6 | C3: 60020011 | D3: =VLOOKUP(C3,codigo!A:B,2,FALSE) -> CAPACITOR CERAMICO .1µF | E3: 100nF Ceramico | F3: Capacitor_THT:C_Disc_D5.0mm_W2.5mm_P2.50mm
A4: C7 | B4: 1 | C4: 60024610 | D4: =VLOOKUP(C4,codigo!A:B,2,FALSE) -> CAPACITOR ELECTROLITICO 1000µF X 16/25V | E4: 1000uF x 16V electrolítico. | F4: Capacitor_THT:CP_Radial_D5.0mm_P2.50mm
A5: D1 | B5: 1 | C5: 60070010 | D5: =VLOOKUP(C5,codigo!A:B,2,FALSE) -> LED ROJO 5 MM | E5: LED Rojo 5mm | F5: LED_THT:LED_D5.0mm
A6: D2,D3 | B6: 2 | C6: 60070019 | D6: MV5439A LED bicolor red/green | E6: MV5439A | F6: LED_THT:LED_D5.0mm-3
A7: J2 | B7: 1 | C7: 60005001 | D7: =VLOOKUP(C7,codigo!A:B,2,FALSE) -> CONECTOR DB 9 HEMBRA P/IMPRESO | E7: DB9 Hembra Impreso 90° | F7: Connector_Dsub:DSUB-9_Socket_Horizontal_P2.77x2.84mm_EdgePinOffset4.94mm_Housed_MountingHolesOffset4.94mm
A8: J3 | B8: 1 | C8: 60004062 | D8: Conector Antena Ufl Smt - Smd X( U.FL macho para PCB(smd) | E8: U.FL IPEX1 MALE | F8: U.FL_Hirose_U.FL-R-SMT-1_Vertical
A9: J4 | B9: 1 | C9: 60004061 | D9: Conector SMA hembra Edge Mount (1.6 mm) (90° Impreso) | E9: SMA-J-P-X-RA-TH1 | F9: SMA-J-P-X-RA-TH1:SAMTEC_SMA-J-P-X-RA-TH1
A10: J5 | B10: 1 | C10: 60004063 | D10: Conector Barrel Jack DC 2.1mm PCB recto | E10: Barrel Jack DC 2.1mm PCB recto | F10: BarrelJack_CUI_PJ-102AH_Horizontal
A11: Q1, Q4 | B11: 2 | C11: 60050002 | D11: =VLOOKUP(C11,codigo!A:B,2,FALSE) -> TRANSISTOR BSS138 SMD | E11: BSS138 | F11: Package_TO_SOT_SMD:SOT-23
A12: Q2, Q3 | B12: 2 | C12: 60052021 | D12: =VLOOKUP(C12,codigo!A:B,2,FALSE) -> FDN340P MOSFET P-CH | E12: FDN340P | F12: Package_TO_SOT_SMD:SOT-23
A13: JP1 a JP7 | B13: 7 | C13: 60002025 | D13: =VLOOKUP(C13,codigo!A:B,2,FALSE) -> TIRA PINES RECTOS 1 X 40 | E13: Jumper 2 pines | F13: Connector_PinHeader_2.54mm:PinHeader_1x02_P2.54mm_Vertical
A14: R15,R17 | B14: 2 | C14: 60012909 | D14: =VLOOKUP(C14,codigo!A:B,2,FALSE) -> 150 OHM RESISTENCIA SMD Formato 0805 | E14: 150 | F14: Resistor_SMD:R_0805_2012Metric_Pad1.20x1.40mm_HandSolder
A15: R14,R16 | B15: 2 | C15: 60012918 | D15: =VLOOKUP(C15,codigo!A:B,2,FALSE) -> 220 OHM RESISTENCIA SMD Formato 0805 | E15: 220 | F15: Resistor_SMD:R_0805_2012Metric_Pad1.20x1.40mm_HandSolder
A16: R7, R12 | B16: 2 | C16: 60012910 | D16: =VLOOKUP(C16,codigo!A:B,2,FALSE) -> 1 KOHM RESISTENCIA SMD Formato 0805 | E16: 1K | F16: Resistor_SMD:R_0805_2012Metric_Pad1.20x1.40mm_HandSolder
A17: R1 | B17: 1 | C17: 60012917 | D17: =VLOOKUP(C17,codigo!A:B,2,FALSE) -> 2.2 KOHM RESISTENCIA SMD Formato 0805 | E17: 2K2 | F17: Resistor_SMD:R_0805_2012Metric_Pad1.20x1.40mm_HandSolder
A18: R2,R4,R9,R13 | B18: 4 | C18: 60012911 | D18: =VLOOKUP(C18,codigo!A:B,2,FALSE) -> RESISTENCIA 4,7 K SMD Formato 0805 | E18: 4K7 | F18: Resistor_SMD:R_0805_2012Metric_Pad1.20x1.40mm_HandSolder
A19: R3, R5, R8, R10 | B19: 4 | C19: 60012921 | D19: =VLOOKUP(C19,codigo!A:B,2,FALSE) -> RESISTENCIA 10 K SMD Formato 0805 | E19: 10K | F19: Resistor_SMD:R_0805_2012Metric_Pad1.20x1.40mm_HandSolder
A20: R6, R11 | B20: 2 | C20: 60012927 | D20: RESISTENCIA 100K SMD Formato 0805 | E20: 100K | F20: Resistor_SMD:R_0805_2012Metric_Pad1.20x1.40mm_HandSolder
A21: U1 | B21: 1 | C21: 60069101 | D21: =VLOOKUP(C21,codigo!A:B,2,FALSE) -> C.I. MAX232CSE SMD | E21: MAX232 | F21: Package_SO:SOIC-16_3.9x9.9mm_P1.27mm
A22: U2 | B22: 1 | C22: 60061005 | D22: =VLOOKUP(C22,codigo!A:B,2,FALSE) -> C.I.AT24C512-10PI MEMORIA EEPROM SERIAL 64KX8 ATME | E22: 24LC512 | F22: Package_SO:SOIC-8_3.9x4.9mm_P1.27mm
A23: U3 | B23: 1 | C23: 60069120 | D23: =VLOOKUP(C23,codigo!A:B,2,FALSE) -> MODULO MICRO TSIM SIMA A7670SA 4G V3 | E23: BKP-A7670SA (Módulo SIMCOM) | F23: Damian_PCB:SimCom_A7670SA
A24: U4 | B24: 1 | C24: 60069122 | D24: MAX706 SOIC8 | E24: MAX706 | F24: Package_SO:SOIC-8_3.9x4.9mm_P1.27mm
A25: U5 | B25: 1 | C25: 60069228 | D25: =VLOOKUP(C25,codigo!A:B,2,FALSE) -> PLACA STM32F401ccu6 ARM Cortex M4 84Mhz 256Kb | E25: Black_Pill_STM32F401CEU6 | F25: Damian_PCB:Black_Pill_STM32F401
A26: U6 | B26: 1 | C26: 70021626 | D26: =VLOOKUP(C26,codigo!A:B,2,FALSE) -> FUENTE STEP DOWN AJUSTABLE 1.25V A 35V LM2596 3A | E26: Step Down LM2596 | F26: Damian_PCB:Modulo Step Down Regulable LM2596
A27: U7 | B27: 1 | C27: 60069049 | D27: =VLOOKUP(C27,codigo!A:B,2,FALSE) -> C.I. MC7805ACT TO220 | E27: LM7805_TO220 | F27: Package_TO_SOT_THT:TO-220-3_Vertical
A28: Cable USSB-C to USB-micro-B (50092319) | C28: 50092319 | D28: =VLOOKUP(C28,codigo!A:B,2,FALSE) -> CABLE MICRO USB M a USBC M | E28: Cable USSB-C to USB-micro-B (50092319)
A29: Cable coaxial Pigtail RF RG178 IPX U.FL a IPX U.FL | C29: 60004064 | D29: Cable coaxial Pigtail RF RG178 IPX U.FL a IPX U.FL (15cm con conector plug en extremos) | E29: Cable coaxial Pigtail RF RG178 IPX U.FL a IPX U.FL
A30: Cable Pigtail coaxial antena 15cm de (U.FL IPX) a SMA hembra | C30: 60004065 | D30: Cable Pigtail U.fl Ipx A Sma Hembra Antena 15 Cm | E30: Cable Pigtail coaxial antena 15cm de (U.FL IPX) a SMA hembra

Sheet codigo
A1: pr_alias | B1: Articulo | C1: Stock Actual | D1: Posicion X | E1: Posicion Y | F1: Posicion Z | G1: Unidad | H1: Punto de Reposicion | I1: Solicitud de compra | J1: OC Sin Aprobar | K1: Orden de compra | L1: Solicitud de Tecnicos | M1: SOC Vs OC
A2: 1111609 | B2: TRAFO 220V a 220V 750 VA | C2: 0 | G2: Unidades | H2: 0 | I2: 0 | J2: 0 | K2: 0 | L2: 0 | M2: 0 | N2: 0
A3: 2021046 | B3: CAP.ELEC.470µF 16V 105° PC | C3: 0 | G3: Unidades | H3: 0 | I3: 0 | J3: 0 | K3: 0 | L3: 0 | M3: 0 | N3: 0
A4: 2021049 | B4: CAP.ELEC.470µF 6.3V 105° PC | C4: 0 | G4: Unidades | H4: 0 | I4: 0 | J4: 0 | K4: 0 | L4: 0 | M4: 0 | N4: 0
A5: 2121877 | B5: C.I. MC9S08sh8cp /J | C5: 0 | G5: Unidades | H5: 0 | I5: 0 | J5: 0 | K5: 0 | L5: 0 | M5: 0 | N5: 0
A6: 2181428 | B6: PLACA PTµC-MF | C6: 0 | G6: Unidades | H6: 0 | I6: 0 | J6: 0 | K6: 0 | L6: 0 | M6: 0 | N6: 0
A7: 2261458 | B7: 82 OHM RESISTENCIA 1/8 W | C7: 0 | D7: A | E7: 3 | F7: D/7 | G7: Unidades | H7: 0 | I7: 0 | J7: 0 | K7: 0 | L7: 0 | M7: 0 | N7: 0
A8: 3093050 | B8: BASTIDOR ABONADO DIGITAL PWR | C8: 0 | G8: Unidades | H8: 0 | I8: 0 | J8: 0 | K8: 0 | L8: 0 | M8: 0 | N8: 0
A9: 5052292 | B9: DISTRIBUIDOR 485 C485-4 4 SALIDAS | C9: 0 | G9: Unidades | H9: 0 | I9: 0 | J9: 0 | K9: 0 | L9: 0 | M9: 0 | N9: 0
A10: 5054153 | B10: RQS4-CPU-2 Replacement, multi-oop/display 2 annun | C10: 0 | G10: Unidades | H10: 0 | I10: 0 | J10: 0 | K10: 0 | L10: 0 | M10: 0 | N10: 0
A11: 10000000 | B11: LOGOTRON III | C11: 0 | D11: E | E11: 8 | F11: A/B | G11: Unidades | H11: 0 | I11: 0 | J11: 0 | K11: 0 | L11: 3 | M11: -3 | N11: -3
A12: 10000001 | B12: LOGOTRON III D | C12: 5 | D12: A | E12: 4 | G12: Unidades | H12: 0 | I12: 0 | J12: 0 | K12: 0 | L12: 8 | M12: -3 | N12: -3
A13: 10000002 | B13: LOGOTRON III D POWER 1 | C13: 1 | D13: A | E13: 4 | G13: Unidades | H13: 0 | I13: 0 | J13: 0 | K13: 0 | L13: 0 | M13: 1 | N13: 1
A14: 10000100 | B14: PROTECTOR TESOROµC - BR | C14: 64 | D14: B | E14: 15 | F14: C | G14: Unidades | H14: 0 | I14: 0 | J14: 0 | K14: 0 | L14: 15 | M14: 49 | N14: 49
A15: 10000101 | B15: PROTECTOR TESOROµC - MF | C15: 71 | D15: B | E15: 15 | F15: C | G15: Unidades | H15: 0 | I15: 0 | J15: 0 | K15: 0 | L15: 38 | M15: 33 | N15: 33
A16: 10000102 | B16: PROTECTOR TESORO µC - MSirena | C16: 30 | D16: B | E16: 15 | F16: E | G16: Unidades | H16: 0 | I16: 0 | J16: 0 | K16: 0 | L16: 1 | M16: 29 | N16: 29
A17: 10000103 | B17: PROTECTOR DE CASTILLETE | C17: 27 | D17: B | E17: 15 | F17: E | G17: Unidades | H17: 0 | I17: 0 | J17: 0 | K17: 0 | L17: 1 | M17: 26 | N17: 26
A18: 10000104 | B18: PROTECTOR DE CASTILLETE PDX | C18: 4 | D18: B | E18: 15 | F18: E | G18: Unidades | H18: 0 | I18: 0 | J18: 0 | K18: 0 | L18: 1 | M18: 3 | N18: 3
A19: 10000105 | B19: PROTECTOR TESORO EXPANSOR | C19: 7 | D19: B | E19: 15 | F19: E | G19: Unidades | H19: 0 | I19: 0 | J19: 0 | K19: 0 | L19: 2 | M19: 5 | N19: 5
A20: 10000106 | B20: PROTECTOR TESORO µC -MF-485 PT AVISADOR | C20: 0 | D20: B | E20: 15 | F20: E | G20: Unidades | H20: 0 | I20: 0 | J20: 0 | K20: 0 | L20: 0 | M20: 0 | N20: 0
A21: 10000150 | B21: MODULO DETECTOR PRESENCIA DE CASTILLETE | C21: 0 | D21: B | E21: 15 | F21: E | G21: Unidades | H21: 0 | I21: 0 | J21: 0 | K21: 0 | L21: 0 | M21: 0 | N21: 0
A22: 10000151 | B22: CAJA RELÉ PT µC - MSirena | C22: 35 | D22: B | E22: 15 | F22: E | G22: Unidades | H22: 0 | I22: 0 | J22: 0 | K22: 0 | L22: 1 | M22: 34 | N22: 34
A23: 10000152 | B23: MODULO DETECTOR PRESENCIA DE CASTILLETE PDX | C23: 1 | D23: B | E23: 15 | F23: E | G23: Unidades | H23: 0 | I23: 0 | J23: 0 | K23: 0 | L23: 0 | M23: 1 | N23: 1
A24: 10000153 | B24: CAJA REPARTIDORA PT | C24: 5 | D24: B | E24: 18 | F24: B | G24: Unidades | H24: 0 | I24: 0 | J24: 0 | K24: 0 | L24: 0 | M24: 5 | N24: 5
A25: 10000200 | B25: RABBIT POS | C25: 0 | G25: Unidades | H25: 0 | I25: 0 | J25: 0 | K25: 0 | L25: 0 | M25: 0 | N25: 0
A26: 10000201 | B26: RABBIT CON PESCADOR | C26: 4 | D26: B | E26: 20 | F26: F | G26: Unidades | H26: 0 | I26: 0 | J26: 0 | K26: 0 | L26: 0 | M26: 4 | N26: 4
A27: 10000202 | B27: RABBIT 2000 TCP/IP | C27: 0 | D27: E | E27: 15 | F27: A | G27: Unidades | H27: 0 | I27: 0 | J27: 0 | K27: 0 | L27: 0 | M27: 0 | N27: 0
A28: 10000203 | B28: RABBIT 3000 TCPIP | C28: 0 | D28: E | E28: 15 | F28: A | G28: Unidades | H28: 0 | I28: 0 | J28: 0 | K28: 0 | L28: 21 | M28: -21 | N28: -21
A29: 10000204 | B29: RABBIT 3200 TIPO M | C29: 114 | D29: B | E29: 19 | F29: D/E/F | G29: Unidades | H29: 0 | I29: 0 | J29: 0 | K29: 0 | L29: 13 | M29: 101 | N29: 101
A30: 10000300 | B30: ABONADO PAP | C30: 0 | D30: A | E30: 4 | G30: Unidades | H30: 0 | I30: 0 | J30: 0 | K30: 0 | L30: 0 | M30: 0 | N30: 0
A31: 10000301 | B31: ABONADO PAP C/RETRANSMISION | C31: 0 | D31: A | E31: 4 | G31: Unidades | H31: 0 | I31: 0 | J31: 0 | K31: 0 | L31: 0 | M31: 0 | N31: 0
A32: 10000310 | B32: COMISARIA PAP | C32: 3 | D32: A | E32: 4 | G32: Unidades | H32: 0 | I32: 0 | J32: 0 | K32: 0 | L32: 1 | M32: 2 | N32: 2
A33: 10000400 | B33: CENTRAL CLASE A DUAL | C33: 0 | G33: Unidades | H33: 0 | I33: 0 | J33: 0 | K33: 0 | L33: 1 | M33: -1 | N33: -1
A34: 10000410 | B34: CENTRAL CLASE B | C34: 5 | D34: A | E34: 4 | G34: Unidades | H34: 0 | I34: 0 | J34: 0 | K34: 0 | L34: 3 | M34: 2 | N34: 2
A35: 10000420 | B35: CENTRAL SIMIL A EN FORMATO CLASE B | C35: 0 | D35: A | E35: 4 | G35: Unidades | H35: 0 | I35: 0 | J35: 0 | K35: 0 | L35: 0 | M35: 0 | N35: 0
A36: 10000440 | B36: NODO DE USUARIO | C36: 0 | G36: Unidades | H36: 0 | I36: 0 | J36: 0 | K36: 0 | L36: 0 | M36: 0 | N36: 0
A37: 10000450 | B37: REPETIDORA SIMPLE | C37: 0 | D37: A | E37: 4 | G37: Unidades | H37: 0 | I37: 0 | J37: 0 | K37: 0 | L37: 0 | M37: 0 | N37: 0
A38: 10000451 | B38: REPETIDORA DOBLE | C38: 0 | G38: Unidades | H38: 0 | I38: 0 | J38: 0 | K38: 0 | L38: 0 | M38: 0 | N38: 0
A39: 10000500 | B39: PULSADOR ASALTO DIGITAL | C39: 566 | D39: B | E39: 15/6 | F39: A/A/BAJO MESA | G39: Unidades | H39: 0 | I39: 0 | J39: 0 | K39: 0 | L39: 31 | M39: 535 | N39: 535
A40: 10000501 | B40: PULSADOR ASALTO DIGITAL MODIFICADO HSBC | C40: 1 | D40: B | E40: 15 | F40: G | G40: Unidades | H40: 0 | I40: 0 | J40: 0 | K40: 0 | L40: 0 | M40: 1 | N40: 1
A41: 10000503 | B41: PULSADOR ASALTO INTELIGENTE | C41: 0 | G41: Unidades | H41: 0 | I41: 0 | J41: 0 | K41: 0 | L41: 0 | M41: 0 | N41: 0
A42: 10000504 | B42: PULSADOR ASALTO CAF | C42: 0 | G42: Unidades | H42: 0 | I42: 0 | J42: 0 | K42: 0 | L42: 0 | M42: 0 | N42: 0
A43: 10000510 | B43: PULSADOR INCENDIO | C43: 0 | D43: B/E | E43: 21/4 | F43: D/A | G43: Unidades | H43: 0 | I43: 0 | J43: 0 | K43: 0 | L43: 3 | M43: -3 | N43: -3
A44: 10000511 | B44: PULSADOR INCENDIO C/TAMPER | C44: 113 | D44: B | E44: 21 | F44: E | G44: Unidades | H44: 0 | I44: 0 | J44: 0 | K44: 0 | L44: 35 | M44: 78 | N44: 78
A45: 10000600 | B45: PLACA DE DISPARO | C45: 80 | D45: B | E45: 16 | F45: F | G45: Unidades | H45: 0 | I45: 0 | J45: 0 | K45: 0 | L45: 13 | M45: 67 | N45: 67
A46: 10000610 | B46: PLACA DE REPORTE | C46: 141 | D46: B | E46: 16 | F46: F | G46: Unidades | H46: 0 | I46: 0 | J46: 0 | K46: 0 | L46: 4 | M46: 137 | N46: 137
A47: 10000611 | B47: PLACA DE REPORTE MODIFICADA HSBC | C47: 54 | D47: B | E47: 16 | F47: F | G47: Unidades | H47: 0 | I47: 0 | J47: 0 | K47: 0 | L47: 0 | M47: 54 | N47: 54
A48: 10000612 | B48: PLACA DE REPORTE SENSADO ALIMENTACION DSC | C48: 104 | D48: B | E48: 16 | F48: F | G48: Unidades | H48: 0 | I48: 0 | J48: 0 | K48: 0 | L48: 1 | M48: 103 | N48: 103
A49: 10000613 | B49: PLACA DE REPORTE MODIFICADA WAVE | C49: 8 | D49: B | E49: 16 | F49: F | G49: Unidades | H49: 0 | I49: 0 | J49: 0 | K49: 0 | L49: 0 | M49: 8 | N49: 8
A50: 10000614 | B50: PLACA DE RELE BALLARDA | C50: 8 | D50: B | E50: 18 | F50: D | G50: Unidades | H50: 0 | I50: 0 | J50: 0 | K50: 0 | L50: 0 | M50: 8 | N50: 8
A51: 10000615 | B51: PLACA DE REPORTE CONTROL PUERTA | C51: 12 | D51: B | E51: 16 | F51: F | G51: Unidades | H51: 0 | I51: 0 | J51: 0 | K51: 0 | L51: 0 | M51: 12 | N51: 12
A52: 10000700 | B52: CAJA CONTROL TAS | C52: 5 | D52: B | E52: 10 | F52: B | G52: Unidades | H52: 0 | I52: 0 | J52: 0 | K52: 0 | L52: 0 | M52: 5 | N52: 5
A53: 10000701 | B53: CAJA RELE TAS | C53: 5 | D53: B | E53: 20 | F53: B | G53: Unidades | H53: 0 | I53: 0 | J53: 0 | K53: 0 | L53: 0 | M53: 5 | N53: 5
A54: 10000900 | B54: BASTIDOR TX KOMBI | C54: 52 | D54: B | E54: MESA | G54: Unidades | H54: 0 | I54: 0 | J54: 0 | K54: 0 | L54: 1 | M54: 51 | N54: 51
A55: 10000901 | B55: BASTIDOR RX KOMBI | C55: 3 | D55: B | E55: MESA | G55: Unidades | H55: 0 | I55: 0 | J55: 0 | K55: 0 | L55: 1 | M55: 2 | N55: 2
A56: 10000902 | B56: CABLE INTERLOCK ABONADO | C56: 104 | D56: B | E56: 34 | F56: D | G56: Unidades | H56: 0 | I56: 0 | J56: 0 | K56: 0 | L56: 2 | M56: 102 | N56: 102
A57: 10010000 | B57: PLACA ABONADO DIGITAL-BR TCPIP | C57: 137 | D57: B | E57: 16 | F57: E | G57: Unidades | H57: 0 | I57: 0 | J57: 0 | K57: 0 | L57: 44 | M57: 93 | N57: 93
A58: 10010001 | B58: PLACA ENTRADA ABONADO OPTO | C58: 229 | D58: B | E58: 19 | F58: A/B | G58: Unidades | H58: 0 | I58: 0 | J58: 0 | K58: 0 | L58: 1 | M58: 228 | N58: 228
A59: 10010002 | B59: PLACA WATCH DOG RF | C59: 252 | D59: B | E59: 16 | F59: G | G59: Unidades | H59: 0 | I59: 0 | J59: 0 | K59: 0 | L59: 6 | M59: 246 | N59: 246
A60: 10010003 | B60: PLACA FUENTE ABONADO DIGITAL | C60: 30 | D60: B | E60: 18 | F60: A/C | G60: Unidades | H60: 0 | I60: 0 | J60: 0 | K60: 0 | L60: 170 | M60: -140 | N60: -140
A61: 10010004 | B61: PLACA ABONADO DIGITAL-BR | C61: 47 | G61: Unidades | H61: 0 | I61: 0 | J61: 0 | K61: 0 | L61: 0 | M61: 47 | N61: 47
A62: 10010005 | B62: PLACA EXPANSIÓN MODEM SERIE | C62: 94 | G62: Unidades | H62: 0 | I62: 0 | J62: 0 | K62: 0 | L62: 10 | M62: 84 | N62: 84
A63: 10010006 | B63: PLACA PTµC-BR | C63: 0 | D63: B | E63: 17 | F63: B | G63: Unidades | H63: 0 | I63: 0 | J63: 0 | K63: 0 | L63: 0 | M63: 0 | N63: 0
A64: 10010007 | B64: PLACA PTµC-MF | C64: 150 | D64: B | E64: 17 | F64: B | G64: Unidades | H64: 0 | I64: 0 | J64: 0 | K64: 0 | L64: 750 | M64: -600 | N64: -600
A65: 10010008 | B65: PLACA ADAPTADORA DE PTµC-BR | C65: 818 | D65: B | E65: 17 | F65: B | G65: Unidades | H65: 0 | I65: 0 | J65: 0 | K65: 0 | L65: 0 | M65: 818 | N65: 818
A66: 10010009 | B66: PLACA ADAPTADORA DE PTµC-MF | C66: 38 | D66: B | E66: 17 | F66: B | G66: Unidades | H66: 0 | I66: 0 | J66: 0 | K66: 0 | L66: 922 | M66: -884 | N66: -884
A67: 10010010 | B67: PLACA ABONADO PAP | C67: 2 | D67: B | E67: 16 | F67: G | G67: Unidades | H67: 0 | I67: 0 | J67: 0 | K67: 0 | L67: 0 | M67: 2 | N67: 2
A68: 10010011 | B68: PLACA COMISARIA PAP | C68: 0 | D68: B | E68: 16 | F68: G | G68: Unidades | H68: 0 | I68: 0 | J68: 0 | K68: 0 | L68: 0 | M68: 0 | N68: 0
A69: 10010012 | B69: PLACA SIRENA PAP | C69: 8 | D69: B | E69: 17 | F69: F | G69: Unidades | H69: 0 | I69: 0 | J69: 0 | K69: 0 | L69: 18 | M69: -10 | N69: -10
A70: 10010013 | B70: PLACA PERIFERICOS DUAL | C70: 8 | D70: B | E70: 16 | F70: D | G70: Unidades | H70: 0 | I70: 0 | J70: 0 | K70: 0 | L70: 32 | M70: -24 | N70: -24
A71: 10010014 | B71: PLACA CPU DUAL | C71: 4 | D71: B | E71: 16 | F71: D | G71: Unidades | H71: 0 | I71: 0 | J71: 0 | K71: 0 | L71: 32 | M71: -28 | N71: -28
A72: 10010015 | B72: PLACA MEDICIONES DUAL | C72: 9 | D72: B | E72: 19 | F72: B | G72: Unidades | H72: 0 | I72: 0 | J72: 0 | K72: 0 | L72: 0 | M72: 9 | N72: 9
A73: 10010016 | B73: PLACA FRONTPANEL B | C73: 11 | D73: B | E73: 17 | F73: D | G73: Unidades | H73: 0 | I73: 0 | J73: 0 | K73: 0 | L73: 41 | M73: -30 | N73: -30
A74: 10010017 | B74: PLACA ADAPTADORA ABO-PDX | C74: 190 | D74: B | E74: 19 | F74: B | G74: Unidades | H74: 0 | I74: 0 | J74: 0 | K74: 0 | L74: 5 | M74: 185 | N74: 185
A75: 10010018 | B75: PLACA BASE RABBIT 3200 | C75: 25 | G75: Unidades | H75: 0 | I75: 0 | J75: 0 | K75: 0 | L75: 18 | M75: 7 | N75: 7
A76: 10010019 | B76: PLACA BASE RABBIT 3000 | C76: 0 | G76: Unidades | H76: 0 | I76: 0 | J76: 0 | K76: 0 | L76: 0 | M76: 0 | N76: 0
A77: 10010020 | B77: PLACA DIORABBIT DX4 | C77: 25 | D77: B | E77: 20 | F77: F | G77: Unidades | H77: 0 | I77: 0 | J77: 0 | K77: 0 | L77: 0 | M77: 25 | N77: 25
A78: 10010021 | B78: RCM3200 MODULE (PLACA RABBIT) | C78: 25 | G78: Unidades | H78: 0 | I78: 0 | J78: 0 | K78: 0 | L78: 0 | M78: 25 | N78: 25
A79: 10010022 | B79: PLACA INDICADORA PAP | C79: 17 | D79: B | E79: 17 | F79: F | G79: Unidades | H79: 0 | I79: 0 | J79: 0 | K79: 0 | L79: 0 | M79: 17 | N79: 17
A80: 10010023 | B80: PLACA ABONADO DIGITAL-BR SIN RETRANSMISION RF | C80: 46 | D80: B | E80: 17 | F80: A | G80: Unidades | H80: 0 | I80: 0 | J80: 0 | K80: 0 | L80: 0 | M80: 46 | N80: 46
A81: 10010024 | B81: PLACA CPU NODO | C81: 0 | D81: B | E81: 16 | F81: C | G81: Unidades | H81: 0 | I81: 0 | J81: 0 | K81: 0 | L81: 0 | M81: 0 | N81: 0
A82: 10010025 | B82: PLACA BACK PANEL NODO | C82: 5 | G82: Unidades | H82: 0 | I82: 0 | J82: 0 | K82: 0 | L82: 0 | M82: 5 | N82: 5
A83: 10010026 | B83: PLACA BACK PANEL DUAL | C83: 36 | D83: B | E83: 17 | F83: E | G83: Unidades | H83: 0 | I83: 0 | J83: 0 | K83: 0 | L83: 1 | M83: 35 | N83: 35
A84: 10010027 | B84: PLACA LED CAJA CONTROL SAS | C84: 15 | D84: B | E84: 20 | F84: C | G84: Unidades | H84: 0 | I84: 0 | J84: 0 | K84: 0 | L84: 0 | M84: 15 | N84: 15
A85: 10010028 | B85: PLACA ADAPTADORA BACK PANEL B | C85: 48 | D85: B | E85: 17 | F85: D | G85: Unidades | H85: 0 | I85: 0 | J85: 0 | K85: 0 | L85: 10 | M85: 38 | N85: 38
A86: 10010029 | B86: PLACA CONTROL SAS1 | C86: 12 | D86: B | E86: 20 | F86: D | G86: Unidades | H86: 0 | I86: 0 | J86: 0 | K86: 0 | L86: 0 | M86: 12 | N86: 12
A87: 10010030 | B87: PLACA CONTROL SAS2 | C87: 1 | D87: B | E87: 19 | F87: B | G87: Unidades | H87: 0 | I87: 0 | J87: 0 | K87: 0 | L87: 20 | M87: -19 | N87: -19
A88: 10010031 | B88: PLACA FUENTE SAS/VITRINAS | C88: 2 | D88: B | E88: 20 | F88: C | G88: Unidades | H88: 0 | I88: 0 | J88: 0 | K88: 0 | L88: 1 | M88: 1 | N88: 1
A89: 10010032 | B89: PLACA BARRERA OPTO2 SAS | C89: 29 | D89: B | E89: 18 | F89: D | G89: Unidades | H89: 0 | I89: 0 | J89: 0 | K89: 0 | L89: 0 | M89: 29 | N89: 29
A90: 10010033 | B90: PLACA EXPERIMENTAL 10X10 | C90: 3 | D90: B | E90: 38 | F90: B | G90: Unidades | H90: 0 | I90: 0 | J90: 0 | K90: 5 | L90: 2 | M90: 6 | N90: 0
A91: 10010034 | B91: PLACA EXPERIMENTAL 10X20 | C91: 1 | D91: B | E91: 38 | F91: B | G91: Unidades | H91: 0 | I91: 0 | J91: 0 | K91: 5 | L91: 3 | M91: 3 | N91: 0
A92: 10010035 | B92: PLACA FRENTE CAJA REPETIDORA | C92: 0 | G92: Unidades | H92: 0 | I92: 0 | J92: 0 | K92: 0 | L92: 0 | M92: 0 | N92: 0
A93: 10010036 | B93: PLACA PROTECTOR VITRINAS 2 | C93: 53 | D93: B | E93: 18 | F93: B | G93: Unidades | H93: 0 | I93: 0 | J93: 0 | K93: 0 | L93: 0 | M93: 53 | N93: 53
A94: 10010037 | B94: PLACA AUTORESET LOGO III | C94: 42 | D94: B | E94: 18 | F94: C | G94: Unidades | H94: 0 | I94: 0 | J94: 0 | K94: 0 | L94: 0 | M94: 42 | N94: 42
A95: 10010038 | B95: PLACA AUTORESET PC | C95: 41 | D95: B | E95: 17 | F95: F | G95: Unidades | H95: 0 | I95: 0 | J95: 0 | K95: 0 | L95: 0 | M95: 41 | N95: 41
A96: 10010039 | B96: PLACA INDICADOR SAFE SYSTEM | C96: 22 | D96: B | E96: 19 | F96: B | G96: Unidades | H96: 0 | I96: 0 | J96: 0 | K96: 0 | L96: 0 | M96: 22 | N96: 22
A97: 10010040 | B97: PLACA TIMER DSC-NORT | C97: 51 | D97: B | E97: 20 | F97: D | G97: Unidades | H97: 0 | I97: 0 | J97: 0 | K97: 0 | L97: 0 | M97: 51 | N97: 51
A98: 10010041 | B98: PLACA RELE2 | C98: 0 | G98: Unidades | H98: 0 | I98: 0 | J98: 0 | K98: 0 | L98: 0 | M98: 0 | N98: 0
A99: 10010042 | B99: PLACA PROTECTOR VITRINAS 1 | C99: 0 | G99: Unidades | H99: 0 | I99: 0 | J99: 0 | K99: 0 | L99: 0 | M99: 0 | N99: 0
A100: 10010043 | B100: PLACA PERIFÉRICO CDT | C100: 3 | D100: B | E100: 17 | F100: E | G100: Unidades | H100: 0 | I100: 0 | J100: 0 | K100: 0 | L100: 0 | M100: 3 | N100: 3
...

Sheet Hoja2
A1: pr_alias | B1: Articulo | C1: Stock Actual | D1: Posicion X | E1: Posicion Y | F1: Posicion Z | G1: Unidad | H1: Punto de Reposicion | I1: Solicitud de compra | J1: OC Sin Aprobar | K1: Orden de compra | L1: Solicitud de Tecnicos | M1: SOC Vs OC
A2: 1111609 | B2: TRAFO 220V a 220V 750 VA | C2: 0 | G2: Unidades | H2: 0 | I2: 0 | J2: 0 | K2: 0 | L2: 0 | M2: 0 | N2: 0
A3: 2021046 | B3: CAP.ELEC.470µF 16V 105° PC | C3: 0 | G3: Unidades | H3: 0 | I3: 0 | J3: 0 | K3: 0 | L3: 0 | M3: 0 | N3: 0
A4: 2021049 | B4: CAP.ELEC.470µF 6.3V 105° PC | C4: 0 | G4: Unidades | H4: 0 | I4: 0 | J4: 0 | K4: 0 | L4: 0 | M4: 0 | N4: 0
A5: 2121877 | B5: C.I. MC9S08sh8cp /J | C5: 0 | G5: Unidades | H5: 0 | I5: 0 | J5: 0 | K5: 0 | L5: 0 | M5: 0 | N5: 0
A6: 2181428 | B6: PLACA PTµC-MF | C6: 0 | G6: Unidades | H6: 0 | I6: 0 | J6: 0 | K6: 0 | L6: 0 | M6: 0 | N6: 0
A7: 2261458 | B7: 82 OHM RESISTENCIA 1/8 W | C7: 0 | D7: A | E7: 3 | F7: D/7 | G7: Unidades | H7: 0 | I7: 0 | J7: 0 | K7: 0 | L7: 0 | M7: 0 | N7: 0
A8: 3093050 | B8: BASTIDOR ABONADO DIGITAL PWR | C8: 0 | G8: Unidades | H8: 0 | I8: 0 | J8: 0 | K8: 0 | L8: 0 | M8: 0 | N8: 0
A9: 5052292 | B9: DISTRIBUIDOR 485 C485-4 4 SALIDAS | C9: 0 | G9: Unidades | H9: 0 | I9: 0 | J9: 0 | K9: 0 | L9: 0 | M9: 0 | N9: 0
A10: 5054153 | B10: RQS4-CPU-2 Replacement, multi-oop/display 2 annun | C10: 0 | G10: Unidades | H10: 0 | I10: 0 | J10: 0 | K10: 0 | L10: 0 | M10: 0 | N10: 0
A11: 10000000 | B11: LOGOTRON III | C11: 0 | D11: E | E11: 8 | F11: A/B | G11: Unidades | H11: 0 | I11: 0 | J11: 0 | K11: 0 | L11: 3 | M11: -3 | N11: -3
A12: 10000001 | B12: LOGOTRON III D | C12: 5 | D12: A | E12: 4 | G12: Unidades | H12: 0 | I12: 0 | J12: 0 | K12: 0 | L12: 8 | M12: -3 | N12: -3
A13: 10000002 | B13: LOGOTRON III D POWER 1 | C13: 1 | D13: A | E13: 4 | G13: Unidades | H13: 0 | I13: 0 | J13: 0 | K13: 0 | L13: 0 | M13: 1 | N13: 1
A14: 10000100 | B14: PROTECTOR TESOROµC - BR | C14: 64 | D14: B | E14: 15 | F14: C | G14: Unidades | H14: 0 | I14: 0 | J14: 0 | K14: 0 | L14: 15 | M14: 49 | N14: 49
A15: 10000101 | B15: PROTECTOR TESOROµC - MF | C15: 71 | D15: B | E15: 15 | F15: C | G15: Unidades | H15: 0 | I15: 0 | J15: 0 | K15: 0 | L15: 38 | M15: 33 | N15: 33
A16: 10000102 | B16: PROTECTOR TESORO µC - MSirena | C16: 30 | D16: B | E16: 15 | F16: E | G16: Unidades | H16: 0 | I16: 0 | J16: 0 | K16: 0 | L16: 1 | M16: 29 | N16: 29
A17: 10000103 | B17: PROTECTOR DE CASTILLETE | C17: 27 | D17: B | E17: 15 | F17: E | G17: Unidades | H17: 0 | I17: 0 | J17: 0 | K17: 0 | L17: 1 | M17: 26 | N17: 26
A18: 10000104 | B18: PROTECTOR DE CASTILLETE PDX | C18: 4 | D18: B | E18: 15 | F18: E | G18: Unidades | H18: 0 | I18: 0 | J18: 0 | K18: 0 | L18: 1 | M18: 3 | N18: 3
A19: 10000105 | B19: PROTECTOR TESORO EXPANSOR | C19: 7 | D19: B | E19: 15 | F19: E | G19: Unidades | H19: 0 | I19: 0 | J19: 0 | K19: 0 | L19: 2 | M19: 5 | N19: 5
A20: 10000106 | B20: PROTECTOR TESORO µC -MF-485 PT AVISADOR | C20: 0 | D20: B | E20: 15 | F20: E | G20: Unidades | H20: 0 | I20: 0 | J20: 0 | K20: 0 | L20: 0 | M20: 0 | N20: 0
A21: 10000150 | B21: MODULO DETECTOR PRESENCIA DE CASTILLETE | C21: 0 | D21: B | E21: 15 | F21: E | G21: Unidades | H21: 0 | I21: 0 | J21: 0 | K21: 0 | L21: 0 | M21: 0 | N21: 0
A22: 10000151 | B22: CAJA RELÉ PT µC - MSirena | C22: 35 | D22: B | E22: 15 | F22: E | G22: Unidades | H22: 0 | I22: 0 | J22: 0 | K22: 0 | L22: 1 | M22: 34 | N22: 34
A23: 10000152 | B23: MODULO DETECTOR PRESENCIA DE CASTILLETE PDX | C23: 1 | D23: B | E23: 15 | F23: E | G23: Unidades | H23: 0 | I23: 0 | J23: 0 | K23: 0 | L23: 0 | M23: 1 | N23: 1
A24: 10000153 | B24: CAJA REPARTIDORA PT | C24: 5 | D24: B | E24: 18 | F24: B | G24: Unidades | H24: 0 | I24: 0 | J24: 0 | K24: 0 | L24: 0 | M24: 5 | N24: 5
A25: 10000200 | B25: RABBIT POS | C25: 0 | G25: Unidades | H25: 0 | I25: 0 | J25: 0 | K25: 0 | L25: 0 | M25: 0 | N25: 0
A26: 10000201 | B26: RABBIT CON PESCADOR | C26: 4 | D26: B | E26: 20 | F26: F | G26: Unidades | H26: 0 | I26: 0 | J26: 0 | K26: 0 | L26: 0 | M26: 4 | N26: 4
A27: 10000202 | B27: RABBIT 2000 TCP/IP | C27: 0 | D27: E | E27: 15 | F27: A | G27: Unidades | H27: 0 | I27: 0 | J27: 0 | K27: 0 | L27: 0 | M27: 0 | N27: 0
A28: 10000203 | B28: RABBIT 3000 TCPIP | C28: 0 | D28: E | E28: 15 | F28: A | G28: Unidades | H28: 0 | I28: 0 | J28: 0 | K28: 0 | L28: 21 | M28: -21 | N28: -21
A29: 10000204 | B29: RABBIT 3200 TIPO M | C29: 114 | D29: B | E29: 19 | F29: D/E/F | G29: Unidades | H29: 0 | I29: 0 | J29: 0 | K29: 0 | L29: 13 | M29: 101 | N29: 101
A30: 10000300 | B30: ABONADO PAP | C30: 0 | D30: A | E30: 4 | G30: Unidades | H30: 0 | I30: 0 | J30: 0 | K30: 0 | L30: 0 | M30: 0 | N30: 0
A31: 10000301 | B31: ABONADO PAP C/RETRANSMISION | C31: 0 | D31: A | E31: 4 | G31: Unidades | H31: 0 | I31: 0 | J31: 0 | K31: 0 | L31: 0 | M31: 0 | N31: 0
A32: 10000310 | B32: COMISARIA PAP | C32: 3 | D32: A | E32: 4 | G32: Unidades | H32: 0 | I32: 0 | J32: 0 | K32: 0 | L32: 1 | M32: 2 | N32: 2
A33: 10000400 | B33: CENTRAL CLASE A DUAL | C33: 0 | G33: Unidades | H33: 0 | I33: 0 | J33: 0 | K33: 0 | L33: 1 | M33: -1 | N33: -1
A34: 10000410 | B34: CENTRAL CLASE B | C34: 5 | D34: A | E34: 4 | G34: Unidades | H34: 0 | I34: 0 | J34: 0 | K34: 0 | L34: 3 | M34: 2 | N34: 2
A35: 10000420 | B35: CENTRAL SIMIL A EN FORMATO CLASE B | C35: 0 | D35: A | E35: 4 | G35: Unidades | H35: 0 | I35: 0 | J35: 0 | K35: 0 | L35: 0 | M35: 0 | N35: 0
A36: 10000440 | B36: NODO DE USUARIO | C36: 0 | G36: Unidades | H36: 0 | I36: 0 | J36: 0 | K36: 0 | L36: 0 | M36: 0 | N36: 0
A37: 10000450 | B37: REPETIDORA SIMPLE | C37: 0 | D37: A | E37: 4 | G37: Unidades | H37: 0 | I37: 0 | J37: 0 | K37: 0 | L37: 0 | M37: 0 | N37: 0
A38: 10000451 | B38: REPETIDORA DOBLE | C38: 0 | G38: Unidades | H38: 0 | I38: 0 | J38: 0 | K38: 0 | L38: 0 | M38: 0 | N38: 0
A39: 10000500 | B39: PULSADOR ASALTO DIGITAL | C39: 566 | D39: B | E39: 15/6 | F39: A/A/BAJO MESA | G39: Unidades | H39: 0 | I39: 0 | J39: 0 | K39: 0 | L39: 31 | M39: 535 | N39: 535
A40: 10000501 | B40: PULSADOR ASALTO DIGITAL MODIFICADO HSBC | C40: 1 | D40: B | E40: 15 | F40: G | G40: Unidades | H40: 0 | I40: 0 | J40: 0 | K40: 0 | L40: 0 | M40: 1 | N40: 1
A41: 10000503 | B41: PULSADOR ASALTO INTELIGENTE | C41: 0 | G41: Unidades | H41: 0 | I41: 0 | J41: 0 | K41: 0 | L41: 0 | M41: 0 | N41: 0
A42: 10000504 | B42: PULSADOR ASALTO CAF | C42: 0 | G42: Unidades | H42: 0 | I42: 0 | J42: 0 | K42: 0 | L42: 0 | M42: 0 | N42: 0
A43: 10000510 | B43: PULSADOR INCENDIO | C43: 0 | D43: B/E | E43: 21/4 | F43: D/A | G43: Unidades | H43: 0 | I43: 0 | J43: 0 | K43: 0 | L43: 3 | M43: -3 | N43: -3
A44: 10000511 | B44: PULSADOR INCENDIO C/TAMPER | C44: 113 | D44: B | E44: 21 | F44: E | G44: Unidades | H44: 0 | I44: 0 | J44: 0 | K44: 0 | L44: 35 | M44: 78 | N44: 78
A45: 10000600 | B45: PLACA DE DISPARO | C45: 80 | D45: B | E45: 16 | F45: F | G45: Unidades | H45: 0 | I45: 0 | J45: 0 | K45: 0 | L45: 13 | M45: 67 | N45: 67
A46: 10000610 | B46: PLACA DE REPORTE | C46: 141 | D46: B | E46: 16 | F46: F | G46: Unidades | H46: 0 | I46: 0 | J46: 0 | K46: 0 | L46: 4 | M46: 137 | N46: 137
A47: 10000611 | B47: PLACA DE REPORTE MODIFICADA HSBC | C47: 54 | D47: B | E47: 16 | F47: F | G47: Unidades | H47: 0 | I47: 0 | J47: 0 | K47: 0 | L47: 0 | M47: 54 | N47: 54
A48: 10000612 | B48: PLACA DE REPORTE SENSADO ALIMENTACION DSC | C48: 104 | D48: B | E48: 16 | F48: F | G48: Unidades | H48: 0 | I48: 0 | J48: 0 | K48: 0 | L48: 1 | M48: 103 | N48: 103
A49: 10000613 | B49: PLACA DE REPORTE MODIFICADA WAVE | C49: 8 | D49: B | E49: 16 | F49: F | G49: Unidades | H49: 0 | I49: 0 | J49: 0 | K49: 0 | L49: 0 | M49: 8 | N49: 8
A50: 10000614 | B50: PLACA DE RELE BALLARDA | C50: 8 | D50: B | E50: 18 | F50: D | G50: Unidades | H50: 0 | I50: 0 | J50: 0 | K50: 0 | L50: 0 | M50: 8 | N50: 8
A51: 10000615 | B51: PLACA DE REPORTE CONTROL PUERTA | C51: 12 | D51: B | E51: 16 | F51: F | G51: Unidades | H51: 0 | I51: 0 | J51: 0 | K51: 0 | L51: 0 | M51: 12 | N51: 12
A52: 10000700 | B52: CAJA CONTROL TAS | C52: 5 | D52: B | E52: 10 | F52: B | G52: Unidades | H52: 0 | I52: 0 | J52: 0 | K52: 0 | L52: 0 | M52: 5 | N52: 5
A53: 10000701 | B53: CAJA RELE TAS | C53: 5 | D53: B | E53: 20 | F53: B | G53: Unidades | H53: 0 | I53: 0 | J53: 0 | K53: 0 | L53: 0 | M53: 5 | N53: 5
A54: 10000900 | B54: BASTIDOR TX KOMBI | C54: 52 | D54: B | E54: MESA | G54: Unidades | H54: 0 | I54: 0 | J54: 0 | K54: 0 | L54: 1 | M54: 51 | N54: 51
A55: 10000901 | B55: BASTIDOR RX KOMBI | C55: 3 | D55: B | E55: MESA | G55: Unidades | H55: 0 | I55: 0 | J55: 0 | K55: 0 | L55: 1 | M55: 2 | N55: 2
A56: 10000902 | B56: CABLE INTERLOCK ABONADO | C56: 104 | D56: B | E56: 34 | F56: D | G56: Unidades | H56: 0 | I56: 0 | J56: 0 | K56: 0 | L56: 2 | M56: 102 | N56: 102
A57: 10010000 | B57: PLACA ABONADO DIGITAL-BR TCPIP | C57: 137 | D57: B | E57: 16 | F57: E | G57: Unidades | H57: 0 | I57: 0 | J57: 0 | K57: 0 | L57: 44 | M57: 93 | N57: 93
A58: 10010001 | B58: PLACA ENTRADA ABONADO OPTO | C58: 229 | D58: B | E58: 19 | F58: A/B | G58: Unidades | H58: 0 | I58: 0 | J58: 0 | K58: 0 | L58: 1 | M58: 228 | N58: 228
A59: 10010002 | B59: PLACA WATCH DOG RF | C59: 252 | D59: B | E59: 16 | F59: G | G59: Unidades | H59: 0 | I59: 0 | J59: 0 | K59: 0 | L59: 6 | M59: 246 | N59: 246
A60: 10010003 | B60: PLACA FUENTE ABONADO DIGITAL | C60: 30 | D60: B | E60: 18 | F60: A/C | G60: Unidades | H60: 0 | I60: 0 | J60: 0 | K60: 0 | L60: 170 | M60: -140 | N60: -140
A61: 10010004 | B61: PLACA ABONADO DIGITAL-BR | C61: 47 | G61: Unidades | H61: 0 | I61: 0 | J61: 0 | K61: 0 | L61: 0 | M61: 47 | N61: 47
A62: 10010005 | B62: PLACA EXPANSIÓN MODEM SERIE | C62: 94 | G62: Unidades | H62: 0 | I62: 0 | J62: 0 | K62: 0 | L62: 10 | M62: 84 | N62: 84
A63: 10010006 | B63: PLACA PTµC-BR | C63: 0 | D63: B | E63: 17 | F63: B | G63: Unidades | H63: 0 | I63: 0 | J63: 0 | K63: 0 | L63: 0 | M63: 0 | N63: 0
A64: 10010007 | B64: PLACA PTµC-MF | C64: 150 | D64: B | E64: 17 | F64: B | G64: Unidades | H64: 0 | I64: 0 | J64: 0 | K64: 0 | L64: 750 | M64: -600 | N64: -600
A65: 10010008 | B65: PLACA ADAPTADORA DE PTµC-BR | C65: 818 | D65: B | E65: 17 | F65: B | G65: Unidades | H65: 0 | I65: 0 | J65: 0 | K65: 0 | L65: 0 | M65: 818 | N65: 818
A66: 10010009 | B66: PLACA ADAPTADORA DE PTµC-MF | C66: 38 | D66: B | E66: 17 | F66: B | G66: Unidades | H66: 0 | I66: 0 | J66: 0 | K66: 0 | L66: 922 | M66: -884 | N66: -884
A67: 10010010 | B67: PLACA ABONADO PAP | C67: 2 | D67: B | E67: 16 | F67: G | G67: Unidades | H67: 0 | I67: 0 | J67: 0 | K67: 0 | L67: 0 | M67: 2 | N67: 2
A68: 10010011 | B68: PLACA COMISARIA PAP | C68: 0 | D68: B | E68: 16 | F68: G | G68: Unidades | H68: 0 | I68: 0 | J68: 0 | K68: 0 | L68: 0 | M68: 0 | N68: 0
A69: 10010012 | B69: PLACA SIRENA PAP | C69: 8 | D69: B | E69: 17 | F69: F | G69: Unidades | H69: 0 | I69: 0 | J69: 0 | K69: 0 | L69: 18 | M69: -10 | N69: -10
A70: 10010013 | B70: PLACA PERIFERICOS DUAL | C70: 8 | D70: B | E70: 16 | F70: D | G70: Unidades | H70: 0 | I70: 0 | J70: 0 | K70: 0 | L70: 32 | M70: -24 | N70: -24
A71: 10010014 | B71: PLACA CPU DUAL | C71: 4 | D71: B | E71: 16 | F71: D | G71: Unidades | H71: 0 | I71: 0 | J71: 0 | K71: 0 | L71: 32 | M71: -28 | N71: -28
A72: 10010015 | B72: PLACA MEDICIONES DUAL | C72: 9 | D72: B | E72: 19 | F72: B | G72: Unidades | H72: 0 | I72: 0 | J72: 0 | K72: 0 | L72: 0 | M72: 9 | N72: 9
A73: 10010016 | B73: PLACA FRONTPANEL B | C73: 11 | D73: B | E73: 17 | F73: D | G73: Unidades | H73: 0 | I73: 0 | J73: 0 | K73: 0 | L73: 41 | M73: -30 | N73: -30
A74: 10010017 | B74: PLACA ADAPTADORA ABO-PDX | C74: 190 | D74: B | E74: 19 | F74: B | G74: Unidades | H74: 0 | I74: 0 | J74: 0 | K74: 0 | L74: 5 | M74: 185 | N74: 185
A75: 10010018 | B75: PLACA BASE RABBIT 3200 | C75: 25 | G75: Unidades | H75: 0 | I75: 0 | J75: 0 | K75: 0 | L75: 18 | M75: 7 | N75: 7
A76: 10010019 | B76: PLACA BASE RABBIT 3000 | C76: 0 | G76: Unidades | H76: 0 | I76: 0 | J76: 0 | K76: 0 | L76: 0 | M76: 0 | N76: 0
A77: 10010020 | B77: PLACA DIORABBIT DX4 | C77: 25 | D77: B | E77: 20 | F77: F | G77: Unidades | H77: 0 | I77: 0 | J77: 0 | K77: 0 | L77: 0 | M77: 25 | N77: 25
A78: 10010021 | B78: RCM3200 MODULE (PLACA RABBIT) | C78: 25 | G78: Unidades | H78: 0 | I78: 0 | J78: 0 | K78: 0 | L78: 0 | M78: 25 | N78: 25
A79: 10010022 | B79: PLACA INDICADORA PAP | C79: 17 | D79: B | E79: 17 | F79: F | G79: Unidades | H79: 0 | I79: 0 | J79: 0 | K79: 0 | L79: 0 | M79: 17 | N79: 17
A80: 10010023 | B80: PLACA ABONADO DIGITAL-BR SIN RETRANSMISION RF | C80: 46 | D80: B | E80: 17 | F80: A | G80: Unidades | H80: 0 | I80: 0 | J80: 0 | K80: 0 | L80: 0 | M80: 46 | N80: 46
A81: 10010024 | B81: PLACA CPU NODO | C81: 0 | D81: B | E81: 16 | F81: C | G81: Unidades | H81: 0 | I81: 0 | J81: 0 | K81: 0 | L81: 0 | M81: 0 | N81: 0
A82: 10010025 | B82: PLACA BACK PANEL NODO | C82: 5 | G82: Unidades | H82: 0 | I82: 0 | J82: 0 | K82: 0 | L82: 0 | M82: 5 | N82: 5
A83: 10010026 | B83: PLACA BACK PANEL DUAL | C83: 36 | D83: B | E83: 17 | F83: E | G83: Unidades | H83: 0 | I83: 0 | J83: 0 | K83: 0 | L83: 1 | M83: 35 | N83: 35
A84: 10010027 | B84: PLACA LED CAJA CONTROL SAS | C84: 15 | D84: B | E84: 20 | F84: C | G84: Unidades | H84: 0 | I84: 0 | J84: 0 | K84: 0 | L84: 0 | M84: 15 | N84: 15
A85: 10010028 | B85: PLACA ADAPTADORA BACK PANEL B | C85: 48 | D85: B | E85: 17 | F85: D | G85: Unidades | H85: 0 | I85: 0 | J85: 0 | K85: 0 | L85: 10 | M85: 38 | N85: 38
A86: 10010029 | B86: PLACA CONTROL SAS1 | C86: 12 | D86: B | E86: 20 | F86: D | G86: Unidades | H86: 0 | I86: 0 | J86: 0 | K86: 0 | L86: 0 | M86: 12 | N86: 12
A87: 10010030 | B87: PLACA CONTROL SAS2 | C87: 1 | D87: B | E87: 19 | F87: B | G87: Unidades | H87: 0 | I87: 0 | J87: 0 | K87: 0 | L87: 20 | M87: -19 | N87: -19
A88: 10010031 | B88: PLACA FUENTE SAS/VITRINAS | C88: 2 | D88: B | E88: 20 | F88: C | G88: Unidades | H88: 0 | I88: 0 | J88: 0 | K88: 0 | L88: 1 | M88: 1 | N88: 1
A89: 10010032 | B89: PLACA BARRERA OPTO2 SAS | C89: 29 | D89: B | E89: 18 | F89: D | G89: Unidades | H89: 0 | I89: 0 | J89: 0 | K89: 0 | L89: 0 | M89: 29 | N89: 29
A90: 10010033 | B90: PLACA EXPERIMENTAL 10X10 | C90: 3 | D90: B | E90: 38 | F90: B | G90: Unidades | H90: 0 | I90: 0 | J90: 0 | K90: 5 | L90: 2 | M90: 6 | N90: 0
A91: 10010034 | B91: PLACA EXPERIMENTAL 10X20 | C91: 1 | D91: B | E91: 38 | F91: B | G91: Unidades | H91: 0 | I91: 0 | J91: 0 | K91: 5 | L91: 3 | M91: 3 | N91: 0
A92: 10010035 | B92: PLACA FRENTE CAJA REPETIDORA | C92: 0 | G92: Unidades | H92: 0 | I92: 0 | J92: 0 | K92: 0 | L92: 0 | M92: 0 | N92: 0
A93: 10010036 | B93: PLACA PROTECTOR VITRINAS 2 | C93: 53 | D93: B | E93: 18 | F93: B | G93: Unidades | H93: 0 | I93: 0 | J93: 0 | K93: 0 | L93: 0 | M93: 53 | N93: 53
A94: 10010037 | B94: PLACA AUTORESET LOGO III | C94: 42 | D94: B | E94: 18 | F94: C | G94: Unidades | H94: 0 | I94: 0 | J94: 0 | K94: 0 | L94: 0 | M94: 42 | N94: 42
A95: 10010038 | B95: PLACA AUTORESET PC | C95: 41 | D95: B | E95: 17 | F95: F | G95: Unidades | H95: 0 | I95: 0 | J95: 0 | K95: 0 | L95: 0 | M95: 41 | N95: 41
A96: 10010039 | B96: PLACA INDICADOR SAFE SYSTEM | C96: 22 | D96: B | E96: 19 | F96: B | G96: Unidades | H96: 0 | I96: 0 | J96: 0 | K96: 0 | L96: 0 | M96: 22 | N96: 22
A97: 10010040 | B97: PLACA TIMER DSC-NORT | C97: 51 | D97: B | E97: 20 | F97: D | G97: Unidades | H97: 0 | I97: 0 | J97: 0 | K97: 0 | L97: 0 | M97: 51 | N97: 51
A98: 10010041 | B98: PLACA RELE2 | C98: 0 | G98: Unidades | H98: 0 | I98: 0 | J98: 0 | K98: 0 | L98: 0 | M98: 0 | N98: 0
A99: 10010042 | B99: PLACA PROTECTOR VITRINAS 1 | C99: 0 | G99: Unidades | H99: 0 | I99: 0 | J99: 0 | K99: 0 | L99: 0 | M99: 0 | N99: 0
A100: 10010043 | B100: PLACA PERIFÉRICO CDT | C100: 3 | D100: B | E100: 17 | F100: E | G100: Unidades | H100: 0 | I100: 0 | J100: 0 | K100: 0 | L100: 0 | M100: 3 | N100: 3
...
